{
    "os": "Linux-5.4.0-153-generic-x86_64-with-glibc2.31",
    "python": "3.10.13",
    "heartbeatAt": "2024-05-01T10:48:00.131679",
    "startedAt": "2024-05-01T10:47:59.550080",
    "docker": null,
    "cuda": null,
    "args": [],
    "state": "running",
    "program": "/raid/home/automathon_2024/account8/automathon-2024/run.py",
    "codePathLocal": "run.py",
    "codePath": "run.py",
    "git": {
        "remote": "git@github.com:ViRoLam/automathon-2024.git",
        "commit": "243b2149e928b967b83cf4f9f492130561dcb0f6"
    },
    "email": null,
    "root": "/raid/home/automathon_2024/account8/automathon-2024",
    "host": "dgxa100",
    "username": "account8",
    "executable": "/usr/bin/python",
    "cpu_count": 64,
    "cpu_count_logical": 128,
    "cpu_freq": {
        "current": 3170.7749375000008,
        "min": 1500.0,
        "max": 2250.0
    },
    "cpu_freq_per_core": [
        {
            "current": 3217.135,
            "min": 1500.0,
            "max": 2250.0
        },
        {
            "current": 3216.94,
            "min": 1500.0,
            "max": 2250.0
        },
        {
            "current": 3217.24,
            "min": 1500.0,
            "max": 2250.0
        },
        {
            "current": 3222.334,
            "min": 1500.0,
            "max": 2250.0
        },
        {
            "current": 3191.93,
            "min": 1500.0,
            "max": 2250.0
        },
        {
            "current": 1609.541,
            "min": 1500.0,
            "max": 2250.0
        },
        {
            "current": 3208.022,
            "min": 1500.0,
            "max": 2250.0
        },
        {
            "current": 3207.974,
            "min": 1500.0,
            "max": 2250.0
        },
        {
            "current": 3216.582,
            "min": 1500.0,
            "max": 2250.0
        },
        {
            "current": 3220.137,
            "min": 1500.0,
            "max": 2250.0
        },
        {
            "current": 3215.987,
            "min": 1500.0,
            "max": 2250.0
        },
        {
            "current": 3219.094,
            "min": 1500.0,
            "max": 2250.0
        },
        {
            "current": 3211.974,
            "min": 1500.0,
            "max": 2250.0
        },
        {
            "current": 1612.512,
            "min": 1500.0,
            "max": 2250.0
        },
        {
            "current": 3231.721,
            "min": 1500.0,
            "max": 2250.0
        },
        {
            "current": 3219.086,
            "min": 1500.0,
            "max": 2250.0
        },
        {
            "current": 3230.168,
            "min": 1500.0,
            "max": 2250.0
        },
        {
            "current": 3215.82,
            "min": 1500.0,
            "max": 2250.0
        },
        {
            "current": 3228.853,
            "min": 1500.0,
            "max": 2250.0
        },
        {
            "current": 3216.522,
            "min": 1500.0,
            "max": 2250.0
        },
        {
            "current": 3198.039,
            "min": 1500.0,
            "max": 2250.0
        },
        {
            "current": 3216.789,
            "min": 1500.0,
            "max": 2250.0
        },
        {
            "current": 3214.26,
            "min": 1500.0,
            "max": 2250.0
        },
        {
            "current": 3218.755,
            "min": 1500.0,
            "max": 2250.0
        },
        {
            "current": 3218.152,
            "min": 1500.0,
            "max": 2250.0
        },
        {
            "current": 3218.28,
            "min": 1500.0,
            "max": 2250.0
        },
        {
            "current": 3218.203,
            "min": 1500.0,
            "max": 2250.0
        },
        {
            "current": 3218.191,
            "min": 1500.0,
            "max": 2250.0
        },
        {
            "current": 3217.269,
            "min": 1500.0,
            "max": 2250.0
        },
        {
            "current": 3218.211,
            "min": 1500.0,
            "max": 2250.0
        },
        {
            "current": 3217.322,
            "min": 1500.0,
            "max": 2250.0
        },
        {
            "current": 3217.374,
            "min": 1500.0,
            "max": 2250.0
        },
        {
            "current": 3217.801,
            "min": 1500.0,
            "max": 2250.0
        },
        {
            "current": 3225.544,
            "min": 1500.0,
            "max": 2250.0
        },
        {
            "current": 3218.211,
            "min": 1500.0,
            "max": 2250.0
        },
        {
            "current": 3218.0,
            "min": 1500.0,
            "max": 2250.0
        },
        {
            "current": 3217.229,
            "min": 1500.0,
            "max": 2250.0
        },
        {
            "current": 3219.728,
            "min": 1500.0,
            "max": 2250.0
        },
        {
            "current": 3218.479,
            "min": 1500.0,
            "max": 2250.0
        },
        {
            "current": 3217.256,
            "min": 1500.0,
            "max": 2250.0
        },
        {
            "current": 3218.679,
            "min": 1500.0,
            "max": 2250.0
        },
        {
            "current": 3218.11,
            "min": 1500.0,
            "max": 2250.0
        },
        {
            "current": 3218.125,
            "min": 1500.0,
            "max": 2250.0
        },
        {
            "current": 3218.003,
            "min": 1500.0,
            "max": 2250.0
        },
        {
            "current": 3218.381,
            "min": 1500.0,
            "max": 2250.0
        },
        {
            "current": 3218.371,
            "min": 1500.0,
            "max": 2250.0
        },
        {
            "current": 3218.319,
            "min": 1500.0,
            "max": 2250.0
        },
        {
            "current": 3218.005,
            "min": 1500.0,
            "max": 2250.0
        },
        {
            "current": 3216.035,
            "min": 1500.0,
            "max": 2250.0
        },
        {
            "current": 3215.896,
            "min": 1500.0,
            "max": 2250.0
        },
        {
            "current": 3216.114,
            "min": 1500.0,
            "max": 2250.0
        },
        {
            "current": 3215.885,
            "min": 1500.0,
            "max": 2250.0
        },
        {
            "current": 3217.267,
            "min": 1500.0,
            "max": 2250.0
        },
        {
            "current": 3217.234,
            "min": 1500.0,
            "max": 2250.0
        },
        {
            "current": 3217.192,
            "min": 1500.0,
            "max": 2250.0
        },
        {
            "current": 3217.254,
            "min": 1500.0,
            "max": 2250.0
        },
        {
            "current": 3218.277,
            "min": 1500.0,
            "max": 2250.0
        },
        {
            "current": 3218.319,
            "min": 1500.0,
            "max": 2250.0
        },
        {
            "current": 3218.32,
            "min": 1500.0,
            "max": 2250.0
        },
        {
            "current": 3218.153,
            "min": 1500.0,
            "max": 2250.0
        },
        {
            "current": 3216.077,
            "min": 1500.0,
            "max": 2250.0
        },
        {
            "current": 3217.204,
            "min": 1500.0,
            "max": 2250.0
        },
        {
            "current": 3217.225,
            "min": 1500.0,
            "max": 2250.0
        },
        {
            "current": 3216.994,
            "min": 1500.0,
            "max": 2250.0
        },
        {
            "current": 3218.042,
            "min": 1500.0,
            "max": 2250.0
        },
        {
            "current": 3218.168,
            "min": 1500.0,
            "max": 2250.0
        },
        {
            "current": 3218.128,
            "min": 1500.0,
            "max": 2250.0
        },
        {
            "current": 3219.02,
            "min": 1500.0,
            "max": 2250.0
        },
        {
            "current": 3206.891,
            "min": 1500.0,
            "max": 2250.0
        },
        {
            "current": 1785.933,
            "min": 1500.0,
            "max": 2250.0
        },
        {
            "current": 3206.663,
            "min": 1500.0,
            "max": 2250.0
        },
        {
            "current": 3206.747,
            "min": 1500.0,
            "max": 2250.0
        },
        {
            "current": 3220.655,
            "min": 1500.0,
            "max": 2250.0
        },
        {
            "current": 3216.724,
            "min": 1500.0,
            "max": 2250.0
        },
        {
            "current": 3235.869,
            "min": 1500.0,
            "max": 2250.0
        },
        {
            "current": 3217.332,
            "min": 1500.0,
            "max": 2250.0
        },
        {
            "current": 3223.28,
            "min": 1500.0,
            "max": 2250.0
        },
        {
            "current": 1608.369,
            "min": 1500.0,
            "max": 2250.0
        },
        {
            "current": 3213.47,
            "min": 1500.0,
            "max": 2250.0
        },
        {
            "current": 3217.036,
            "min": 1500.0,
            "max": 2250.0
        },
        {
            "current": 3219.254,
            "min": 1500.0,
            "max": 2250.0
        },
        {
            "current": 3218.238,
            "min": 1500.0,
            "max": 2250.0
        },
        {
            "current": 3218.276,
            "min": 1500.0,
            "max": 2250.0
        },
        {
            "current": 3218.269,
            "min": 1500.0,
            "max": 2250.0
        },
        {
            "current": 3217.132,
            "min": 1500.0,
            "max": 2250.0
        },
        {
            "current": 3218.004,
            "min": 1500.0,
            "max": 2250.0
        },
        {
            "current": 2961.879,
            "min": 1500.0,
            "max": 2250.0
        },
        {
            "current": 3217.208,
            "min": 1500.0,
            "max": 2250.0
        },
        {
            "current": 3217.048,
            "min": 1500.0,
            "max": 2250.0
        },
        {
            "current": 3217.054,
            "min": 1500.0,
            "max": 2250.0
        },
        {
            "current": 3217.428,
            "min": 1500.0,
            "max": 2250.0
        },
        {
            "current": 3216.92,
            "min": 1500.0,
            "max": 2250.0
        },
        {
            "current": 3216.748,
            "min": 1500.0,
            "max": 2250.0
        },
        {
            "current": 3217.184,
            "min": 1500.0,
            "max": 2250.0
        },
        {
            "current": 3217.24,
            "min": 1500.0,
            "max": 2250.0
        },
        {
            "current": 3217.137,
            "min": 1500.0,
            "max": 2250.0
        },
        {
            "current": 3215.132,
            "min": 1500.0,
            "max": 2250.0
        },
        {
            "current": 3215.536,
            "min": 1500.0,
            "max": 2250.0
        },
        {
            "current": 3215.485,
            "min": 1500.0,
            "max": 2250.0
        },
        {
            "current": 3215.298,
            "min": 1500.0,
            "max": 2250.0
        },
        {
            "current": 3217.133,
            "min": 1500.0,
            "max": 2250.0
        },
        {
            "current": 3217.161,
            "min": 1500.0,
            "max": 2250.0
        },
        {
            "current": 3217.164,
            "min": 1500.0,
            "max": 2250.0
        },
        {
            "current": 3217.269,
            "min": 1500.0,
            "max": 2250.0
        },
        {
            "current": 3215.536,
            "min": 1500.0,
            "max": 2250.0
        },
        {
            "current": 3215.505,
            "min": 1500.0,
            "max": 2250.0
        },
        {
            "current": 3215.628,
            "min": 1500.0,
            "max": 2250.0
        },
        {
            "current": 3215.212,
            "min": 1500.0,
            "max": 2250.0
        },
        {
            "current": 3217.356,
            "min": 1500.0,
            "max": 2250.0
        },
        {
            "current": 3217.351,
            "min": 1500.0,
            "max": 2250.0
        },
        {
            "current": 3217.154,
            "min": 1500.0,
            "max": 2250.0
        },
        {
            "current": 3217.076,
            "min": 1500.0,
            "max": 2250.0
        },
        {
            "current": 3215.567,
            "min": 1500.0,
            "max": 2250.0
        },
        {
            "current": 3215.683,
            "min": 1500.0,
            "max": 2250.0
        },
        {
            "current": 3215.695,
            "min": 1500.0,
            "max": 2250.0
        },
        {
            "current": 3215.562,
            "min": 1500.0,
            "max": 2250.0
        },
        {
            "current": 3217.369,
            "min": 1500.0,
            "max": 2250.0
        },
        {
            "current": 3217.277,
            "min": 1500.0,
            "max": 2250.0
        },
        {
            "current": 3217.227,
            "min": 1500.0,
            "max": 2250.0
        },
        {
            "current": 3217.398,
            "min": 1500.0,
            "max": 2250.0
        },
        {
            "current": 3217.151,
            "min": 1500.0,
            "max": 2250.0
        },
        {
            "current": 3217.025,
            "min": 1500.0,
            "max": 2250.0
        },
        {
            "current": 3216.826,
            "min": 1500.0,
            "max": 2250.0
        },
        {
            "current": 3216.389,
            "min": 1500.0,
            "max": 2250.0
        },
        {
            "current": 3216.649,
            "min": 1500.0,
            "max": 2250.0
        },
        {
            "current": 3216.749,
            "min": 1500.0,
            "max": 2250.0
        },
        {
            "current": 3216.705,
            "min": 1500.0,
            "max": 2250.0
        },
        {
            "current": 3216.89,
            "min": 1500.0,
            "max": 2250.0
        }
    ],
    "disk": {
        "/": {
            "total": 1757.8785285949707,
            "used": 375.65476989746094
        }
    },
    "gpu": "NVIDIA A100-SXM4-80GB",
    "gpu_count": 5,
    "gpu_devices": [
        {
            "name": "NVIDIA A100-SXM4-80GB",
            "memory_total": 85899345920
        },
        {
            "name": "NVIDIA A100-SXM4-80GB",
            "memory_total": 85899345920
        },
        {
            "name": "NVIDIA A100-SXM4-80GB",
            "memory_total": 85899345920
        },
        {
            "name": "NVIDIA DGX Display",
            "memory_total": 4294967296
        },
        {
            "name": "NVIDIA A100-SXM4-80GB",
            "memory_total": 85899345920
        }
    ],
    "memory": {
        "total": 503.7273750305176
    }
}
